IndicPhotoOCR/__init__.py
IndicPhotoOCR/ocr.py
IndicPhotoOCR/detection/__init__.py
IndicPhotoOCR/detection/east_config.py
IndicPhotoOCR/detection/east_detector.py
IndicPhotoOCR/detection/east_locality_aware_nms.py
IndicPhotoOCR/detection/east_model.py
IndicPhotoOCR/detection/east_preprossing.py
IndicPhotoOCR/detection/east_utils.py
IndicPhotoOCR/detection/textbpn/__init__.py
IndicPhotoOCR/detection/textbpn/textbpnpp_detector.py
IndicPhotoOCR/detection/textbpn/network/Reg_loss.py
IndicPhotoOCR/detection/textbpn/network/Seg_loss.py
IndicPhotoOCR/detection/textbpn/network/__init__.py
IndicPhotoOCR/detection/textbpn/network/loss.py
IndicPhotoOCR/detection/textbpn/network/loss_org.py
IndicPhotoOCR/detection/textbpn/network/textnet.py
IndicPhotoOCR/detection/textbpn/network/backbone/__init__.py
IndicPhotoOCR/detection/textbpn/network/backbone/resnet.py
IndicPhotoOCR/detection/textbpn/network/backbone/vgg.py
IndicPhotoOCR/detection/textbpn/network/layers/Adaptive_Deformation.py
IndicPhotoOCR/detection/textbpn/network/layers/CircConv.py
IndicPhotoOCR/detection/textbpn/network/layers/GCN.py
IndicPhotoOCR/detection/textbpn/network/layers/GraphConv.py
IndicPhotoOCR/detection/textbpn/network/layers/RNN.py
IndicPhotoOCR/detection/textbpn/network/layers/Transformer.py
IndicPhotoOCR/detection/textbpn/network/layers/Transformer_old.py
IndicPhotoOCR/detection/textbpn/network/layers/__init__.py
IndicPhotoOCR/detection/textbpn/network/layers/gcn_utils.py
IndicPhotoOCR/detection/textbpn/network/layers/model_block.py
IndicPhotoOCR/detection/textbpn/network/layers/position_encoding.py
IndicPhotoOCR/detection/textbpn/network/layers/resnet.py
IndicPhotoOCR/detection/textbpn/network/layers/resnet_dcn.py
IndicPhotoOCR/detection/textbpn/network/layers/vgg.py
IndicPhotoOCR/detection/textbpn/util/__init__.py
IndicPhotoOCR/detection/textbpn/util/augmentation.py
IndicPhotoOCR/detection/textbpn/util/canvas.py
IndicPhotoOCR/detection/textbpn/util/detection.py
indicphotoocr-1.3.1.dist-info/licenses/LICENSE
indicphotoocr-1.3.1.dist-info/METADATA
indicphotoocr-1.3.1.dist-info/WHEEL
indicphotoocr-1.3.1.dist-info/top_level.txt
indicphotoocr-1.3.1.dist-info/RECORD
