Metadata-Version: 2.4
Name: IndicPhotoOCR
Version: 1.3.1
Summary: Scene Text Recognition Toolkit across 13 Indian Languages which contains detection, script identification, and text recognition modules
Home-page: https://github.com/Bhashini-IITJ/IndicPhotoOCR
Author: Anik De
Author-email: anekde@gmail.com
Requires-Python: >=3.9
License-File: LICENSE
Requires-Dist: aiohappyeyeballs==2.4.3
Requires-Dist: aiohttp==3.10.11
Requires-Dist: aiosignal==1.3.1
Requires-Dist: async-timeout==4.0.3
Requires-Dist: attrs==24.2.0
Requires-Dist: certifi==2024.8.30
Requires-Dist: charset-normalizer==3.4.0
Requires-Dist: click==8.1.7
Requires-Dist: datasets==3.1.0
Requires-Dist: filelock==3.16.1
Requires-Dist: frozenlist==1.5.0
Requires-Dist: fsspec==2024.9.0
Requires-Dist: huggingface-hub==0.26.1
Requires-Dist: idna==3.10
Requires-Dist: jinja2==3.1.5
Requires-Dist: joblib==1.4.2
Requires-Dist: lightning-utilities==0.11.8
Requires-Dist: markupsafe==3.0.2
Requires-Dist: mpmath==1.3.0
Requires-Dist: multidict==6.1.0
Requires-Dist: networkx==3.2.1
Requires-Dist: nltk==3.9.1
Requires-Dist: numpy==1.26.4
Requires-Dist: packaging==24.1
Requires-Dist: pillow==11.0.0
Requires-Dist: propcache==0.2.0
Requires-Dist: pytorch-lightning==2.4.0
Requires-Dist: pyyaml==6.0.2
Requires-Dist: regex==2024.9.11
Requires-Dist: requests==2.32.3
Requires-Dist: safetensors==0.4.5
Requires-Dist: sympy==1.13.1
Requires-Dist: timm==1.0.11
Requires-Dist: torchmetrics==1.5.1
Requires-Dist: transformers==4.48.0
Requires-Dist: tqdm==4.66.5
Requires-Dist: typing-extensions==4.12.2
Requires-Dist: urllib3==2.2.3
Requires-Dist: yarl==1.16.0
Requires-Dist: opencv-python==4.10.0.84
Requires-Dist: shapely==2.0.6
Requires-Dist: openai-clip==1.0.1
Requires-Dist: lmdb==1.5.1
Requires-Dist: easydict==1.13
Requires-Dist: scipy==1.13.1
Requires-Dist: six==1.16.0
Requires-Dist: matplotlib==3.9.0
Provides-Extra: cu118
Requires-Dist: torch==2.5.0+cu118; extra == "cu118"
Requires-Dist: torchvision==0.20.0+cu118; extra == "cu118"
Provides-Extra: cu121
Requires-Dist: torch==2.5.0+cu121; extra == "cu121"
Requires-Dist: torchvision==0.20.0+cu121; extra == "cu121"
Provides-Extra: cpu
Requires-Dist: torch==2.5.0; extra == "cpu"
Requires-Dist: torchvision==0.20.0; extra == "cpu"
Dynamic: author
Dynamic: author-email
Dynamic: description
Dynamic: description-content-type
Dynamic: home-page
Dynamic: license-file
Dynamic: provides-extra
Dynamic: requires-dist
Dynamic: requires-python
Dynamic: summary
